{
    "local_variable": {
        "999870468": {
            "variable_dict": {}, 
            "variable_length_dict": {}
        }, 
        "1007525889": {
            "variable_dict": {}, 
            "variable_length_dict": {}
        }, 
        "1267642371": {
            "variable_dict": {}, 
            "variable_length_dict": {}
        }, 
        "1876426754": {
            "variable_dict": {}, 
            "variable_length_dict": {}
        }
    }, 
    "trigger_dict": {
        "999870468": {
            "action": [
                {
                    "action_type": "ADD_ATTR", 
                    "args_list": [
                        {
                            "arg_type": 100006, 
                            "args_list": [], 
                            "sub_type": "ABILITY_OWNER"
                        }, 
                        {
                            "arg_type": 100300, 
                            "args_list": [
                                "ATTR_BONUS"
                            ], 
                            "sub_type": 1
                        }, 
                        {
                            "arg_type": 100042, 
                            "args_list": [
                                "V37jHJdxEe+Sgy9VeiiygP"
                            ], 
                            "sub_type": 1
                        }, 
                        {
                            "arg_type": 100000, 
                            "args_list": [
                                10.0
                            ], 
                            "sub_type": 1
                        }
                    ], 
                    "bp": false, 
                    "element_id": 999870468000002, 
                    "enable": true
                }
            ], 
            "call_enabled": true, 
            "condition": [], 
            "enabled": false, 
            "event": [
                {
                    "args_list": [], 
                    "element_id": 999870468000001, 
                    "enable": true, 
                    "event_type": "UNIT_END_NAV_EVENT"
                }
            ], 
            "group_id": 134263474, 
            "is_conf": true, 
            "p_trigger_id": 1876426754, 
            "sub_trigger_owner_set_var_action": {
                "action_type": "SET_VARIABLE", 
                "args_list": [
                    {
                        "arg_type": 100178, 
                        "args_list": [
                            {
                                "__tuple__": true, 
                                "items": [
                                    "DYNAMIC_TRIGGER_INSTANCE", 
                                    "\u517b\u7cbe\u84c4\u9510\u7ad9\u7acb\u56de\u8840", 
                                    "actor"
                                ]
                            }
                        ], 
                        "sub_type": "VARIABLE"
                    }, 
                    {
                        "arg_type": 100178, 
                        "args_list": [
                            {
                                "arg_type": 100068, 
                                "args_list": [
                                    999870468
                                ], 
                                "sub_type": 1
                            }
                        ], 
                        "sub_type": "REG_ABILITY_TRIGGER"
                    }
                ], 
                "bp": false, 
                "element_id": 1267642371000020, 
                "enable": true
            }, 
            "trigger_id": 999870468, 
            "trigger_name": "\u5b50\u89e6\u53d1\u5668_2", 
            "valid": true, 
            "var_data": [
                {}, 
                {}, 
                []
            ]
        }, 
        "1007525889": {
            "action": [
                {
                    "action_type": "UNREG_TRIGGER", 
                    "args_list": [
                        {
                            "arg_type": 100178, 
                            "args_list": [
                                {
                                    "__tuple__": true, 
                                    "items": [
                                        "DYNAMIC_TRIGGER_INSTANCE", 
                                        "\u517b\u7cbe\u84c4\u9510\u79fb\u52a8\u505c\u6b62\u56de\u8840", 
                                        "actor"
                                    ]
                                }
                            ], 
                            "sub_type": "VARIABLE"
                        }
                    ], 
                    "bp": false, 
                    "element_id": 1007525889000005, 
                    "enable": true
                }, 
                {
                    "action_type": "UNREG_TRIGGER", 
                    "args_list": [
                        {
                            "arg_type": 100178, 
                            "args_list": [
                                {
                                    "__tuple__": true, 
                                    "items": [
                                        "DYNAMIC_TRIGGER_INSTANCE", 
                                        "\u517b\u7cbe\u84c4\u9510\u7ad9\u7acb\u56de\u8840", 
                                        "actor"
                                    ]
                                }
                            ], 
                            "sub_type": "VARIABLE"
                        }
                    ], 
                    "bp": false, 
                    "element_id": 1007525889000010, 
                    "enable": true
                }, 
                {
                    "action_type": "CALL_TRIGGER_FUNC", 
                    "args_list": [
                        {
                            "arg_type": 100177, 
                            "args_list": [
                                {
                                    "arg_type": 100002, 
                                    "args_list": [
                                        {
                                            "arg_type": 100014, 
                                            "args_list": [], 
                                            "sub_type": "CUR_ABILITY"
                                        }, 
                                        {
                                            "arg_type": 100003, 
                                            "args_list": [
                                                "\u5361\u724cID\u503c"
                                            ], 
                                            "sub_type": 1
                                        }
                                    ], 
                                    "sub_type": "GET_INTEGER_KV"
                                }, 
                                {
                                    "arg_type": 100006, 
                                    "args_list": [], 
                                    "sub_type": "ABILITY_OWNER"
                                }
                            ], 
                            "op_arg": [], 
                            "op_arg_enable": [], 
                            "sub_type": "878525343d5611f08b85092c5b0204bc"
                        }
                    ], 
                    "bp": false, 
                    "call_rt_arg_idxes": [], 
                    "element_id": 1007525889000002, 
                    "enable": true
                }
            ], 
            "call_enabled": true, 
            "condition": [], 
            "enabled": true, 
            "event": [
                {
                    "args_list": [], 
                    "element_id": 1007525889000001, 
                    "enable": true, 
                    "event_type": "ABILITY_LOSE"
                }
            ], 
            "group_id": 134263474, 
            "p_trigger_id": null, 
            "trigger_id": 1007525889, 
            "trigger_name": "\u5931\u53bb\u65f6", 
            "valid": true, 
            "var_data": [
                {}, 
                {}, 
                []
            ]
        }, 
        "1267642371": {
            "action": [
                {
                    "action_type": "ADD_ATTR", 
                    "args_list": [
                        {
                            "arg_type": 100006, 
                            "args_list": [], 
                            "sub_type": "ABILITY_OWNER"
                        }, 
                        {
                            "arg_type": 100300, 
                            "args_list": [
                                "ATTR_BONUS"
                            ], 
                            "sub_type": 1
                        }, 
                        {
                            "arg_type": 100042, 
                            "args_list": [
                                "V37jHJdxEe+Sgy9VeiiygP"
                            ], 
                            "sub_type": 1
                        }, 
                        {
                            "arg_type": 100000, 
                            "args_list": [
                                -10.0
                            ], 
                            "sub_type": 1
                        }
                    ], 
                    "bp": false, 
                    "element_id": 1876426754000008, 
                    "enable": true
                }
            ], 
            "call_enabled": true, 
            "condition": [], 
            "enabled": false, 
            "event": [
                {
                    "args_list": [], 
                    "element_id": 1267642371000010, 
                    "enable": true, 
                    "event_type": "UNIT_START_NAV_EVENT"
                }
            ], 
            "group_id": 134263474, 
            "is_conf": true, 
            "p_trigger_id": 1876426754, 
            "sub_trigger_owner_set_var_action": {
                "action_type": "SET_VARIABLE", 
                "args_list": [
                    {
                        "arg_type": 100178, 
                        "args_list": [
                            [
                                "DYNAMIC_TRIGGER_INSTANCE", 
                                "\u517b\u7cbe\u84c4\u9510\u79fb\u52a8\u505c\u6b62\u56de\u8840", 
                                "actor"
                            ]
                        ], 
                        "sub_type": "VARIABLE"
                    }, 
                    {
                        "arg_type": 100178, 
                        "args_list": [
                            {
                                "arg_type": 100068, 
                                "args_list": [
                                    1267642371
                                ], 
                                "sub_type": 1
                            }
                        ], 
                        "sub_type": "REG_ABILITY_TRIGGER"
                    }
                ], 
                "bp": false, 
                "element_id": 1267642371000020, 
                "enable": true
            }, 
            "trigger_id": 1267642371, 
            "trigger_name": "\u5b50\u89e6\u53d1\u5668", 
            "valid": true, 
            "var_data": [
                {}, 
                {}, 
                []
            ]
        }, 
        "1876426754": {
            "action": [
                {
                    "action_type": "CALL_TRIGGER_FUNC", 
                    "args_list": [
                        {
                            "arg_type": 100177, 
                            "args_list": [
                                {
                                    "arg_type": 100002, 
                                    "args_list": [
                                        {
                                            "arg_type": 100014, 
                                            "args_list": [], 
                                            "sub_type": "CUR_ABILITY"
                                        }, 
                                        {
                                            "arg_type": 100003, 
                                            "args_list": [
                                                "\u5361\u724cID\u503c"
                                            ], 
                                            "sub_type": 1
                                        }
                                    ], 
                                    "sub_type": "GET_INTEGER_KV"
                                }, 
                                {
                                    "arg_type": 100006, 
                                    "args_list": [], 
                                    "sub_type": "ABILITY_OWNER"
                                }
                            ], 
                            "op_arg": [], 
                            "op_arg_enable": [], 
                            "sub_type": "c4b7ecc53d5511f0a540092c5b0204bc"
                        }
                    ], 
                    "bp": false, 
                    "call_rt_arg_idxes": [], 
                    "element_id": 1876426754000002, 
                    "enable": true
                }, 
                {
                    "action_type": "ADD_ATTR", 
                    "args_list": [
                        {
                            "arg_type": 100006, 
                            "args_list": [], 
                            "sub_type": "ABILITY_OWNER"
                        }, 
                        {
                            "arg_type": 100300, 
                            "args_list": [
                                "ATTR_BONUS"
                            ], 
                            "sub_type": 1
                        }, 
                        {
                            "arg_type": 100042, 
                            "args_list": [
                                "V37jHJdxEe+Sgy9VeiiygP"
                            ], 
                            "sub_type": 1
                        }, 
                        {
                            "arg_type": 100000, 
                            "args_list": [
                                10.0
                            ], 
                            "sub_type": 1
                        }
                    ], 
                    "bp": false, 
                    "element_id": 1876426754000008, 
                    "enable": true
                }, 
                1267642371, 
                999870468
            ], 
            "call_enabled": true, 
            "condition": [], 
            "enabled": true, 
            "event": [
                {
                    "args_list": [], 
                    "element_id": 1876426754000001, 
                    "enable": true, 
                    "event_type": "ABILITY_OBTAIN"
                }
            ], 
            "group_id": 134263474, 
            "p_trigger_id": null, 
            "trigger_id": 1876426754, 
            "trigger_name": "\u83b7\u5f97\u65f6", 
            "valid": true, 
            "var_data": [
                {}, 
                {}, 
                []
            ]
        }
    }, 
    "trigger_group_info": [
        {
            "_trigger_group_": true, 
            "group": [
                {
                    "__tuple__": true, 
                    "items": [
                        1876426754, 
                        "\u83b7\u5f97\u65f6"
                    ]
                }, 
                {
                    "__tuple__": true, 
                    "items": [
                        1007525889, 
                        "\u5931\u53bb\u65f6"
                    ]
                }
            ], 
            "key": 134263474, 
            "name": "134263474"
        }, 
        {
            "__tuple__": true, 
            "items": [
                1267642371, 
                "\u5b50\u89e6\u53d1\u5668"
            ]
        }, 
        {
            "__tuple__": true, 
            "items": [
                999870468, 
                "\u5b50\u89e6\u53d1\u5668_2"
            ]
        }
    ], 
    "trigger_version": "1.2", 
    "variable_dict": {
        "DYNAMIC_TRIGGER_INSTANCE": {
            "\u517b\u7cbe\u84c4\u9510\u79fb\u52a8\u505c\u6b62\u56de\u8840": 0, 
            "\u517b\u7cbe\u84c4\u9510\u7ad9\u7acb\u56de\u8840": 0
        }
    }, 
    "variable_group_info": [
        {
            "__tuple__": true, 
            "items": [
                "\u517b\u7cbe\u84c4\u9510\u79fb\u52a8\u505c\u6b62\u56de\u8840", 
                "\u517b\u7cbe\u84c4\u9510\u79fb\u52a8\u505c\u6b62\u56de\u8840"
            ]
        }, 
        {
            "__tuple__": true, 
            "items": [
                "\u517b\u7cbe\u84c4\u9510\u7ad9\u7acb\u56de\u8840", 
                "\u517b\u7cbe\u84c4\u9510\u7ad9\u7acb\u56de\u8840"
            ]
        }
    ], 
    "variable_length_dict": {
        "\u517b\u7cbe\u84c4\u9510\u79fb\u52a8\u505c\u6b62\u56de\u8840": 0, 
        "\u517b\u7cbe\u84c4\u9510\u7ad9\u7acb\u56de\u8840": 0
    }
}