{
    "custom_editor_type": "custom_editor_icon", 
    "describe": "", 
    "has_upload": false, 
    "key": 134270132, 
    "md5": "1a711d91f5536c3e0373bb331f75ef69", 
    "name": "\u65b9\u5f62_0044_\u5b50\u5348\u9488\u7078\u7ecf", 
    "path": "ui/134270132", 
    "res_name": "\u65b9\u5f62_0044_\u5b50\u5348\u9488\u7078\u7ecf.png", 
    "size": "128X128", 
    "sub_type": "icon", 
    "uid": "134270132", 
    "url": "https://kk3.nosdn.127.net/editor/png/c7c4bda22b6e4d458a8ae73d4375011c.png", 
    "version": 1
}